[{"post_title":"在CMD、BAT批次檔使用MD新增、建立資料夾","post_url":"cmd-create-folder"},{"post_title":"Windows 10關閉動畫效果幫電腦、顯卡加速教學","post_url":"windows-10-disable-animation-effect"},{"post_title":"BiliBili(嗶哩嗶哩)台灣破解地區封鎖限制教學","post_url":"unblock-bilibili"},{"post_title":"Windows 10關閉背景應用程式讓電腦更快更順暢","post_url":"windows-10-disable-background-app"},{"post_title":"Windows 10暫時暫停、停止自動更新教學","post_url":"windows-10-pause-update"},{"post_title":"BiliBili(嗶哩嗶哩)影片超清晰高畫質下載教學","post_url":"bilibili-download-video"},{"post_title":"XAMPP更改Apache HTTP連線預設端口80 Port教學","post_url":"xampp-change-apache-http-port"},{"post_title":"Windows 10幫使用者帳戶新增設定密碼教學","post_url":"windows-10-add-account-password"},{"post_title":"Windows 10自動安裝、更新硬體設備驅動程式教學","post_url":"windows-10-install-drivers"},{"post_title":"Windows作業系統清除DNS快取教學","post_url":"windows-flush-dns-cache"},{"post_title":"Windows 10開啟刪除檔案確認提示對話框教學","post_url":"windows-10-delete-confirm"},{"post_title":"在CMD、BAT批次檔使用RD刪除指定資料夾","post_url":"cmd-delete-folder"},{"post_title":"在CMD、BAT使用START執行任意檔案、開啟網站網址或程式","post_url":"cmd-execute-program"},{"post_title":"NameCheap開啟域名隱私保護功能","post_url":"namecheap-whoisguard"},{"post_title":"中文姓名、名字線上翻譯成英文姓名","post_url":"name-to-english"},{"post_title":"線上將影片快速轉為GIF動態圖片教學","post_url":"video-to-gif"},{"post_title":"Windows 10螢幕顏色變暗變黃變橘解決辦法","post_url":"windows-10-display-night-time"},{"post_title":"Windows 10變更、更改使用者帳戶密碼教學","post_url":"windows-10-change-account-password"},{"post_title":"NVIDIA顯示卡優化、加速設定教學","post_url":"nvidia-optimization"},{"post_title":"NameCheap將域名加入CloudFlare DNS代管設定教學","post_url":"namecheap-with-cloudflare"},{"post_title":"Windows 10 Edge瀏覽器更改檔案預設下載資料夾位置","post_url":"change-edge-download-path"},{"post_title":"Sony手機無法開機或一直重開機解決辦法","post_url":"reset-sony-mobile"},{"post_title":"Windows 10電腦麥克風有雜音、噪音解決辦法","post_url":"windows-10-microphone-noise"},{"post_title":"Windows 10將我的電腦新增到桌面教學","post_url":"windows-10-add-computer-to-desktop"},{"post_title":"將PicPick語言更改設定成繁體中文、中文化教學","post_url":"change-picpick-language"},{"post_title":"Windows 10繁體中文正版原版ISO檔案從微軟官網下載教學","post_url":"download-windows-10-iso"},{"post_title":"Windows 10更改電源計劃設定提高電腦運作效能","post_url":"windows-10-full-power"},{"post_title":"在Windows 10電腦讓日期顯示月曆、農民曆、台灣國定節慶教學","post_url":"windows-10-lunar-calendar"},{"post_title":"Sony Xperia手機當機沒反應，強制關機教學","post_url":"force-shutdown-sony-mobile"},{"post_title":"Twitch影片線上快速、高解析度高清下載教學","post_url":"download-twitch-video"},{"post_title":"Windows 10使用DDU完整移除顯示卡驅動程式教學","post_url":"windows-10-remove-display-driver"},{"post_title":"IIS Express資料庫連線速度很慢優化方法","post_url":"optimizing-iis-express"},{"post_title":"中文地址線上翻譯成英文地址","post_url":"address-to-english"},{"post_title":"Windows 10關閉自動播放避免使用隨身碟或光碟而中毒","post_url":"windows-10-disable-autoplay"},{"post_title":"YouTube影片線上轉換成GIF動畫圖片教學","post_url":"youtube-to-gif"},{"post_title":"查看電腦RAM記憶體是否已啟用雙通道教學","post_url":"check-ram-dual-channel"},{"post_title":"永久關閉Windows 10的Windows Defender","post_url":"disable-windows-10-defender"},{"post_title":"網站或網址被Facebook封鎖解決辦法","post_url":"url-blocked-by-facebook"},{"post_title":"在CMD、BAT批次檔使用DEL刪除指定檔案","post_url":"cmd-delete-files"},{"post_title":"Windows 10使用語音聊天時電腦、遊戲聲音變小解決辦法","post_url":"windows-10-sound-auto-adjust"},{"post_title":"Windows 10找不到瑞昱高傳真音效控制面板解決辦法","post_url":"windows-10-realtek-setting"},{"post_title":"NameCheap註冊帳號教學","post_url":"singup-namecheap"},{"post_title":"Windows 10永久關閉、停用Windows電腦自動更新教學","post_url":"windows-10-disable-update"},{"post_title":"XAMPP更改Apache HTTPS連線預設端口443 Port教學","post_url":"xampp-change-apache-https-port"},{"post_title":"更改CMD、BAT批次檔視窗標題教學","post_url":"change-cmd-title"},{"post_title":"Windows 10進入控制台與新增控制台捷徑到桌面方法","post_url":"windows-10-control-panel"},{"post_title":"Windows 10關閉自動更新、安裝驅動程式教學","post_url":"windows-10-disable-auto-driver"},{"post_title":"更改CMD、BAT批次檔文字、背景顏色教學","post_url":"change-cmd-color"},{"post_title":"Windows 10移除使用者帳戶密碼教學","post_url":"windows-10-remove-account-password"},{"post_title":"Windows 10使用Google DNS幫網路、網頁加速","post_url":"windows-10-google-dns"},{"post_title":"Windows 10調整字體大小讓文字變大教學","post_url":"windows-10-font-size"},{"post_title":"Windows 10麥克風講話、錄音聲音很小聲解決辦法","post_url":"windows-10-microphone-volume"},{"post_title":"NameCheap購買網域、域名教學","post_url":"namecheap-domain-name-registration"}]