[{"post_title":"Windows 10移除使用者帳戶密碼教學","post_url":"windows-10-remove-account-password"},{"post_title":"Windows 10麥克風講話、錄音聲音很小聲解決辦法","post_url":"windows-10-microphone-volume"},{"post_title":"Windows 10調整字體大小讓文字變大教學","post_url":"windows-10-font-size"},{"post_title":"Windows 10電腦麥克風有雜音、噪音解決辦法","post_url":"windows-10-microphone-noise"},{"post_title":"在Windows 10電腦讓日期顯示月曆、農民曆、台灣國定節慶教學","post_url":"windows-10-lunar-calendar"},{"post_title":"Windows 10找不到瑞昱高傳真音效控制面板解決辦法","post_url":"windows-10-realtek-setting"}]